pesapal/__init__.py
pesapal/client.py
pesapal/constants.py
pesapal/exceptions.py
pesapal/models.py
pesapal/utils.py
pesapal_python_sdk-1.0.0.dist-info/licenses/LICENSE
pesapal_python_sdk-1.0.0.dist-info/METADATA
pesapal_python_sdk-1.0.0.dist-info/WHEEL
pesapal_python_sdk-1.0.0.dist-info/top_level.txt
pesapal_python_sdk-1.0.0.dist-info/RECORD
