Metadata-Version: 2.4
Name: pesapal-python-sdk
Version: 1.0.0
Summary: Python SDK for Pesapal Payment Gateway API 3.0
Home-page: https://github.com/erickblema/pesapal-python-sdk
Author: Erick Lema
Author-email: Erick Lema <ericklema360@gmail.com>
License-Expression: MIT
Project-URL: Homepage, https://github.com/erickblema/pesapal-python-sdk
Project-URL: Documentation, https://github.com/erickblema/pesapal-python-sdk#readme
Project-URL: Repository, https://github.com/erickblema/pesapal-python-sdk
Project-URL: Issues, https://github.com/erickblema/pesapal-python-sdk/issues
Keywords: pesapal,payment,gateway,sdk,api,fintech
Classifier: Development Status :: 4 - Beta
Classifier: Intended Audience :: Developers
Classifier: Programming Language :: Python :: 3
Classifier: Programming Language :: Python :: 3.8
Classifier: Programming Language :: Python :: 3.9
Classifier: Programming Language :: Python :: 3.10
Classifier: Programming Language :: Python :: 3.11
Classifier: Programming Language :: Python :: 3.12
Classifier: Topic :: Software Development :: Libraries :: Python Modules
Classifier: Topic :: Office/Business :: Financial
Requires-Python: >=3.8
License-File: LICENSE
Requires-Dist: httpx>=0.24.0
Requires-Dist: pydantic>=2.0.0
Provides-Extra: dev
Requires-Dist: pytest>=7.0.0; extra == "dev"
Requires-Dist: pytest-asyncio>=0.21.0; extra == "dev"
Requires-Dist: black>=23.0.0; extra == "dev"
Requires-Dist: ruff>=0.1.0; extra == "dev"
Dynamic: author
Dynamic: home-page
Dynamic: license-file
Dynamic: requires-python
